deepsynth_gitract/__init__.py
deepsynth_gitract/deepsynth_gitract.py
deepsynth_gitract-0.0.1.dist-info/LICENSE
deepsynth_gitract-0.0.1.dist-info/METADATA
deepsynth_gitract-0.0.1.dist-info/WHEEL
deepsynth_gitract-0.0.1.dist-info/top_level.txt
deepsynth_gitract-0.0.1.dist-info/RECORD
